hyperstack/__init__.py
hyperstack/api_client.py
hyperstack/api_response.py
hyperstack/configuration.py
hyperstack/exceptions.py
hyperstack/py.typed
hyperstack/rest.py
hyperstack/api/__init__.py
hyperstack/api/alive_api.py
hyperstack/api/api_key_api.py
hyperstack/api/assigning_member_role_api.py
hyperstack/api/auth_api.py
hyperstack/api/billing_api.py
hyperstack/api/calculate_api.py
hyperstack/api/callbacks_api.py
hyperstack/api/cluster_events_api.py
hyperstack/api/clusters_api.py
hyperstack/api/compliance_api.py
hyperstack/api/credit_api.py
hyperstack/api/customer_contract_api.py
hyperstack/api/dashboard_api.py
hyperstack/api/deployment_api.py
hyperstack/api/environment_api.py
hyperstack/api/firewall_attachment_api.py
hyperstack/api/firewalls_api.py
hyperstack/api/flavor_api.py
hyperstack/api/floating_ip_api.py
hyperstack/api/gpu_api.py
hyperstack/api/image_api.py
hyperstack/api/invite_api.py
hyperstack/api/keypair_api.py
hyperstack/api/organization_api.py
hyperstack/api/payment_api.py
hyperstack/api/permission_api.py
hyperstack/api/policy_api.py
hyperstack/api/pricebook_api.py
hyperstack/api/profile_api.py
hyperstack/api/rbac_role_api.py
hyperstack/api/region_api.py
hyperstack/api/security_rules_api.py
hyperstack/api/snapshot_events_api.py
hyperstack/api/snapshots_api.py
hyperstack/api/stock_api.py
hyperstack/api/template_api.py
hyperstack/api/user_api.py
hyperstack/api/user_detail_choice_api.py
hyperstack/api/user_permission_api.py
hyperstack/api/virtual_machine_api.py
hyperstack/api/virtual_machine_events_api.py
hyperstack/api/vnc_url_api.py
hyperstack/api/volume_api.py
hyperstack/api/volume_attachment_api.py
hyperstack/models/__init__.py
hyperstack/models/add_update_flavor_organization_payload.py
hyperstack/models/add_user_info_success_response_model.py
hyperstack/models/admin_add_update_image_organization_payload.py
hyperstack/models/admin_bootstrap_environment_payload.py
hyperstack/models/admin_cluster_resource.py
hyperstack/models/admin_container_resource.py
hyperstack-0.3.0.dist-info/METADATA
hyperstack-0.3.0.dist-info/WHEEL
hyperstack-0.3.0.dist-info/top_level.txt
hyperstack-0.3.0.dist-info/RECORD
